

{
  "cpuinfo": {
    "syscall": "open",
    "errno": -2,
    "code": "ENOENT",
    "path": "\/proc\/cpuinfo"
  },
  "dmesg": {
    "cmd": "dmesg",
    "signal": null,
    "code": 1,
    "killed": false
  },
  "df": "Filesystem      Size   Used  Avail Capacity iused      ifree %iused  Mounted on\n\/dev\/disk1     465Gi   50Gi  415Gi    11% 1001258 4293966021    0%   \/\ndevfs          205Ki  205Ki    0Bi   100%     710          0  100%   \/dev\nmap -hosts       0Bi    0Bi    0Bi   100%       0          0  100%   \/net\nmap auto_home    0Bi    0Bi    0Bi   100%       0          0  100%   \/home\n",
  "timestamp": 1489679828,
  "\/etc\/issue": {
    "syscall": "open",
    "errno": -2,
    "code": "ENOENT",
    "path": "\/etc\/issue"
  },
  "uname": "Darwin akrug-28119 16.4.0 Darwin Kernel Version 16.4.0: Thu Dec 22 22:53:21 PST 2016; root:xnu-3789.41.3~3\/RELEASE_X86_64 x86_64\n",
  "pwd": "\/Users\/akrug\/workspace\/node-lambda-inspector\n",
  "env": {
    "rvm_version": "1.29.1 (latest)",
    "rvm_path": "\/Users\/akrug\/.rvm",
    "TERM_PROGRAM_VERSION": "3.0.14",
    "RUBY_VERSION": "ruby-2.4.0",
    "LOGNAME": "akrug",
    "USER": "akrug",
    "HOME": "\/Users\/akrug",
    "PATH": "\/Users\/akrug\/.rvm\/gems\/ruby-2.4.0\/bin:\/Users\/akrug\/.rvm\/gems\/ruby-2.4.0@global\/bin:\/Users\/akrug\/.rvm\/rubies\/ruby-2.4.0\/bin:\/usr\/local\/bin:\/usr\/bin:\/bin:\/usr\/sbin:\/sbin:\/usr\/local\/MacGPG2\/bin:\/Applications\/Muse:\/Users\/akrug\/.rvm\/bin",
    "TERM_PROGRAM": "iTerm.app",
    "LANG": "en_US.UTF-8",
    "TERM": "xterm-256color",
    "SHELL": "\/bin\/bash",
    "COLORFGBG": "11;15",
    "SHLVL": "1",
    "_system_name": "OSX",
    "XPC_FLAGS": "0x0",
    "ITERM_SESSION_ID": "w0t0p0:54508761-C4E3-45B9-A4C7-672E70458021",
    "_": "\/usr\/local\/bin\/node",
    "_system_arch": "x86_64",
    "GEM_PATH": "\/Users\/akrug\/.rvm\/gems\/ruby-2.4.0:\/Users\/akrug\/.rvm\/gems\/ruby-2.4.0@global",
    "DYLD_FALLBACK_LIBRARY_PATH": ":\/Applications\/Muse",
    "rvm_bin_path": "\/Users\/akrug\/.rvm\/bin",
    "TERM_SESSION_ID": "w0t0p0:54508761-C4E3-45B9-A4C7-672E70458021",
    "XPC_SERVICE_NAME": "0",
    "rvm_prefix": "\/Users\/akrug",
    "SSH_AUTH_SOCK": "\/private\/tmp\/com.apple.launchd.bzXtf0XaQn\/Listeners",
    "IRBRC": "\/Users\/akrug\/.rvm\/rubies\/ruby-2.4.0\/.irbrc",
    "_system_type": "Darwin",
    "MY_RUBY_HOME": "\/Users\/akrug\/.rvm\/rubies\/ruby-2.4.0",
    "Apple_PubSub_Socket_Render": "\/private\/tmp\/com.apple.launchd.5sr8uClue0\/Render",
    "ITERM_PROFILE": "Default",
    "TMPDIR": "\/var\/folders\/94\/jsn9sl851nqgkyqn5gyc_b_h0000gn\/T\/",
    "OLDPWD": "\/Users\/akrug\/workspace",
    "__CF_USER_TEXT_ENCODING": "0x1F5:0:0",
    "PWD": "\/Users\/akrug\/workspace\/node-lambda-inspector",
    "_system_version": "10.12",
    "GEM_HOME": "\/Users\/akrug\/.rvm\/gems\/ruby-2.4.0"
  },
  "runtime": "nodejs",
  "ps": "USER               PID  %CPU %MEM      VSZ    RSS   TT  STAT STARTED      TIME COMMAND\nakrug            40992   9.6  0.1  3087296  21496 s000  R+    8:57AM   0:00.11 node profiler.js\nakrug            40122   4.9  2.0  3875528 340188   ??  S     8:14AM   2:58.16 \/Applications\/Atom.app\/Contents\/Frameworks\/Atom Helper.app\/Contents\/MacOS\/Atom Helper --type=renderer --no-sandbox --primordial-pipe-token=331D9FBD6F8493C9919F0CE7F67119F6 --lang=en-US --node-integration=true --background-color=#fff --hidden-page --enable-pinch --num-raster-threads=2 --enable-zero-copy --disable-partial-raster --enable-gpu-memory-buffer-compositor-resources --content-image-texture-target=3553,3553,3553,3553,3553,34037,3553,3553,3553,3553,3553,34037,3553,34037,34037 --video-image-texture-target=3553,3553,3553,3553,3553,34037,3553,3553,3553,3553,3553,34037,3553,34037,34037 --mojo-channel-token=946A7C397486F0C8419903EB06BB54A5 --mojo-application-channel-token=A75625C721146FB7F51E02FBBBA089CE --channel=39978.2.37854516\nakrug            39880   4.2 10.2  7411968 1707356   ??  S     8:11AM  11:10.26 \/Applications\/Firefox.app\/Contents\/MacOS\/firefox\nakrug            39894   4.1  0.7  2827308 115616   ??  S     8:12AM   1:07.29 \/Applications\/iTerm.app\/Contents\/MacOS\/iTerm2\n_windowserver      154   3.8  1.8  4116756 297900   ??  Ss   Tue08AM  59:50.00 \/System\/Library\/PrivateFrameworks\/SkyLight.framework\/Resources\/WindowServer -daemon\nakrug            39978   2.0  0.8  3725108 128748   ??  S     8:13AM   1:08.16 \/Applications\/Atom.app\/Contents\/MacOS\/Atom\nakrug             6920   0.6  2.2  5807436 376672   ??  S    Wed08AM  23:05.66 \/Applications\/FirefoxDeveloperEdition.app\/Contents\/MacOS\/plugin-container.app\/Contents\/MacOS\/plugin-container -childID 1 -isForBrowser -intPrefs 5:50|6:-1|18:0|28:1000|33:20|34:10|43:128|44:10000|48:0|50:400|51:1|52:0|53:0|58:0|59:120|60:120|133:2|134:1|147:5000|157:0|159:0|170:10000|195:24|196:32768|198:0|199:0|207:5|211:1048576|212:100|213:5000|215:600|226:1|241:60000| -boolPrefs 1:0|2:1|4:0|26:1|27:1|30:0|35:1|36:0|37:0|38:0|39:1|40:0|41:1|42:1|45:0|46:0|47:0|49:0|54:1|55:1|56:1|57:1|61:1|62:1|63:0|64:1|65:1|66:1|67:1|70:0|71:0|74:1|75:1|79:1|80:1|81:1|82:0|84:0|85:0|86:1|87:0|90:0|91:1|92:1|93:1|94:1|95:1|96:0|97:1|98:1|99:0|100:1|101:0|102:1|103:1|104:0|105:1|106:1|107:1|108:0|109:1|110:1|111:1|112:0|113:1|114:1|115:1|116:1|117:1|118:1|119:1|120:1|122:0|123:0|124:0|125:1|126:0|127:1|131:1|132:1|135:1|136:0|141:0|146:0|149:1|151:0|152:1|154:1|158:0|162:0|164:1|165:1|171:0|172:0|173:1|175:0|186:0|193:0|194:0|197:1|200:0|202:1|204:1|205:0|210:0|214:1|219:0|220:0|221:0|222:1|224:1|225:1|228:1|233:0|234:0|235:1|236:1|237:0|238:1|239:1|240:1|242:0|243:0|245:1|253:1|254:0|255:0|256:0|257:0| -stringPrefs 3:6:aurora|174:3:1.0|191:332: \\240\u00bc\u00bd\u00be\u01c3\u02d0\u0337\u0338\u0589\u058a\u05c3\u05f4^F^I^F^J\u066a\u06d4\u0701\u0702\u0703\u0704\u115f\u1160\u1735\\040^@\\040^A\\040^B\\040^C\\040^D\\040^E\\040^F\\040^G\\040^H\\040^I\\040^J\\040^K\\040^N\\040^O\u2010\u2019\u2024\u2027\\040-(\\040-)\\040-*\\040-+\\040-,\\040--\\040-.\\040-\/\u2039\u203a\u2041\u2044\u2052\\040-_\u2153\u2154\u2155\u2156\u2157\u2158\u2159\u215a\u215b\u215c\u215d\u215e\u215f\u2215\u2236\u23ae\u2571\u29f6\u29f8\u2afb\u2afd\u2ff0\u2ff1\u2ff2\u2ff3\u2ff4\u2ff5\u2ff6\u2ff7\u2ff8\u2ff9\u2ffa\u2ffb-0^@\u3002\u3014\u3015\u3033\u30a0\u3164-2^]-2^^\u33ae\u33af\u33c6-3M-_M-'M^IM-~^TM-~^U\ufe3f\ufe5d\ufe5eM-~M^?\uff0e\uff0f\uff61\uffa0M^?M-yM^?M-zM^?M-{\ufffc\ufffd|192:8:moderate|227:38:{5df6a0b3-4fcf-c34e-b0dc-fbdbff88d152}| -greomni \/Applications\/FirefoxDeveloperEdition.app\/Contents\/Resources\/omni.ja -appomni \/Applications\/FirefoxDeveloperEdition.app\/Contents\/Resources\/browser\/omni.ja -appdir \/Applications\/FirefoxDeveloperEdition.app\/Contents\/Resources\/browser -profile \/Users\/akrug\/Library\/Application Support\/Firefox\/Profiles\/jyemmr24.dev-edition-default 6919 gecko-crash-server-pipe.6919 org.mozilla.machname.995126448 tab\nakrug             6919   0.5  4.3  6371956 722820   ??  S    Wed08AM  16:53.88 \/Applications\/FirefoxDeveloperEdition.app\/Contents\/MacOS\/firefox\n_hidd              104   0.5  0.0  2474052   6296   ??  Ss   Tue08AM  14:33.21 \/usr\/libexec\/hidd\nakrug            39979   0.2  0.3  2880608  47276   ??  S     8:13AM   0:26.79 \/Applications\/Atom.app\/Contents\/Frameworks\/Atom Helper.app\/Contents\/MacOS\/Atom Helper --type=gpu-process --channel=39978.0.1569094679 --mojo-application-channel-token=822BD0D1A089256394922DF90EF87154 --no-sandbox --supports-dual-gpus=false --gpu-driver-bug-workarounds=16,21,25,36,47,50,51,55,57,65,66,72,75 --gpu-vendor-id=0x8086 --gpu-device-id=0x1927 --gpu-driver-vendor --gpu-driver-version --gpu-driver-date --gpu-active-vendor-id=0x8086 --gpu-active-device-id=0x1927\nroot               384   0.2  0.0  2495732   6420   ??  Ss   Tue08AM   0:01.87 \/usr\/libexec\/taskgated -s\nakrug            39898   0.2  0.0  2461044   3244 s000  S     8:12AM   0:00.18 -bash\nroot               263   0.1  0.1  2499196   8620   ??  Ss   Tue08AM   0:26.86 \/System\/Library\/PrivateFrameworks\/PerformanceAnalysis.framework\/Versions\/A\/XPCServices\/com.apple.PerformanceAnalysis.animationperfd.xpc\/Contents\/MacOS\/com.apple.PerformanceAnalysis.animationperfd\nakrug            10676   0.1  3.2  4720492 542576   ??  S     3:35PM  69:32.12 \/Applications\/Screenhero.app\/Contents\/MacOS\/Screenhero\nakrug              470   0.1  0.1  2534504  11676   ??  S    Tue08AM   0:25.51 \/System\/Library\/CoreServices\/Siri.app\/Contents\/MacOS\/Siri launchd\nakrug              403   0.1  0.0  2497224   6864   ??  S    Tue08AM   0:25.02 \/System\/Library\/PrivateFrameworks\/ViewBridge.framework\/Versions\/A\/XPCServices\/ViewBridgeAuxiliary.xpc\/Contents\/MacOS\/ViewBridgeAuxiliary\nakrug              288   0.1  0.8  2726220 130144   ??  S    Tue08AM   0:49.54 \/System\/Library\/CoreServices\/Dock.app\/Contents\/MacOS\/Dock\nakrug            37198   0.1  1.1  3300056 182588   ??  S     6:13PM   6:27.76 \/Applications\/Google Chrome.app\/Contents\/MacOS\/Google Chrome\n_spotlight       40262   0.0  0.0  2476572   5868   ??  S     8:20AM   0:00.05 \/System\/Library\/Frameworks\/CoreServices.framework\/Frameworks\/Metadata.framework\/Versions\/A\/Support\/mdworker -s mdworker -c MDSImporterWorker -m com.apple.mdworker.shared\nakrug            40178   0.0  0.3  3155480  48972   ??  S     8:14AM   0:00.29 \/Applications\/Atom.app\/Contents\/Frameworks\/Atom Helper.app\/Contents\/MacOS\/Atom Helper --eval require('\/Applications\/Atom.app\/Contents\/Resources\/app.asar\/src\/compile-cache.js').setCacheDirectory('\/Users\/akrug\/.atom\/compile-cache');\\012require('\/Applications\/Atom.app\/Contents\/Resources\/app.asar\/src\/task-bootstrap.js');\nakrug            39981   0.0  0.0  2471384   3108   ??  S     8:13AM   0:00.01 \/Applications\/Atom.app\/Contents\/Frameworks\/Electron Framework.framework\/Resources\/crashpad_handler --database=\/tmp\/Atom Crashes --url=https:\/\/crashreporter.atom.io --handshake-fd=42\nroot             39897   0.0  0.0  2469468   2740 s000  S     8:12AM   0:00.03 login -fp akrug\nakrug            39896   0.0  0.0  2471844   5524 s000  Ss    8:12AM   0:00.02 \/Applications\/iTerm.app\/Contents\/MacOS\/iTerm2 --server login -fp akrug\nakrug            39888   0.0  0.1  2518396  12256   ??  Ss    8:12AM   0:00.10 \/System\/Library\/Frameworks\/VideoToolbox.framework\/Versions\/A\/XPCServices\/VTDecoderXPCService.xpc\/Contents\/MacOS\/VTDecoderXPCService\nakrug            39881   0.0  0.1  2534200  13660   ??  S     8:11AM   0:00.15 \/System\/Library\/CoreServices\/CoreServicesUIAgent.app\/Contents\/MacOS\/CoreServicesUIAgent\nroot             39794   0.0  0.0  2500568   6260   ??  Ss    8:10AM   0:11.36 \/usr\/sbin\/bluetoothaudiod\nroot             39727   0.0  0.0  2495080   4392   ??  Ss    4:32AM   0:00.88 \/usr\/sbin\/ocspd\n_netbios         39657   0.0  0.0  2471740   4884   ??  SNs   2:31AM   0:00.05 \/usr\/sbin\/netbiosd\nroot             37384   0.0  0.0  2471412   3228   ??  Ss    6:50PM   0:00.45 \/usr\/sbin\/cupsd -l\nakrug            37209   0.0  0.2  3252460  34324   ??  S     6:13PM   0:01.66 \/Applications\/Google Chrome.app\/Contents\/Versions\/56.0.2924.87\/Google Chrome Helper.app\/Contents\/MacOS\/Google Chrome Helper --type=renderer --enable-features=AutofillProfileCleanup<AutofillProfileCleanup,BlockSmallPluginContent<PluginPowerSaverTiny,EnableSyncClientToServerCompression<EnableSyncClientToServerCompression,*ExpectCTReporting<ExpectCTReporting,*NegotiateTLS13<TLS13Negotiation,ParseHTMLOnMainThread<ParseHTMLOnMainThread,*PersistentHistograms<PersistentHistograms,*PointerEvent<PointerEvent,PreferHtmlOverPlugins<Html5ByDefault,*PrioritySupportedRequestsDelayable<NetDelayableH2AndQuicRequests,SecurityChip<SecurityChip,SecurityWarningIconUpdate<SecurityWarningIconUpdate,SubresourceFilter<SubresourceFilter,*TranslateRankerLogging<TranslateRankerLogging,ViewsSimplifiedFullscreenUI<ViewsSimplifiedFullscreenUI --disable-features=DocumentWriteEvaluator<DisallowFetchForDocWrittenScriptsInMainFrame,SSLPostQuantumExperiment<SSLPostQuantum --force-fieldtrials=*AppBannerTriggering\/site-engagement-eager\/*AutofillProfileCleanup\/Enabled\/CaptivePortalInterstitial\/Enabled\/*ChromeChannelStable\/Enabled\/*ChromeSuggestionsTuning\/Default\/*ClientSideDetectionModel\/Model0\/DataReductionProxyUseQuic\/ControlForTcpLowat\/*DisallowFetchForDocWrittenScriptsInMainFrame\/Control_20161208_Launch\/EnableSyncClientToServerCompression\/Enabled\/ExpectCTReporting\/ExpectCTReportingDisabled\/ExtensionDeveloperModeWarning\/Enabled\/*ExtensionInstallVerification\/Enforce\/Html5ByDefault\/Enabled2\/*InstanceID\/Enabled\/MarkNonSecureAs\/show-non-secure-passwords-cc-ui\/*NetDelayableH2AndQuicRequests\/Default\/OfferUploadCreditCards\/Enabled\/*OmniboxBundledExperimentV1\/StandardR7\/*ParseHTMLOnMainThread\/Default\/PasswordBranding\/SmartLockBrandingSavePromptOnly\/*PasswordGeneration\/Disabled\/*PasswordManagerSettingsMigration\/Enable\/*PersistentHistograms\/Default\/PluginPowerSaverTiny\/Enabled2\/*QUIC\/EnabledNoId\/ReportCertificateErrors\/ShowAndPossiblySend\/SHA1IdentityUIWarning\/Enabled\/SHA1ToolbarUIJanuary2016\/Warning\/SHA1ToolbarUIJanuary2017\/Error\/SSLCommonNameMismatchHandling\/Enabled\/*SSLPostQuantum\/disabled\/*SafeBrowsingIncidentReportingService\/Default\/SafeBrowsingUnverifiedDownloads\/DisableByParameterMostSbTypes2\/SafeBrowsingV4LocalDatabaseManagerEnabled\/Default\/*SaveAsMenuText\/default\/*SecurityChip\/Enabled\/SecurityWarningIconUpdate\/Enabled2\/SignInPasswordPromo\/Enable3\/*SiteIsolationExtensions\/Enabled_100\/StrictSecureCookies\/Enabled\/*SubresourceFilter\/EnabledForPhishingSites\/*TLS13Negotiation\/Default\/TranslateRankerLogging\/TranslateRankerLoggingDefault\/TranslateServerStudy\/Default\/*UMA-Dynamic-Uniformity-Trial\/Group3\/*UMA-Population-Restrict\/normal\/*UMA-Uniformity-Trial-1-Percent\/group_11\/*UMA-Uniformity-Trial-10-Percent\/group_05\/*UMA-Uniformity-Trial-100-Percent\/group_01\/*UMA-Uniformity-Trial-20-Percent\/group_03\/*UMA-Uniformity-Trial-5-Percent\/group_11\/*UMA-Uniformity-Trial-50-Percent\/default\/*WebFontsInterventionV2\/Default\/ --primordial-pipe-token=12A8150786C5051C0C97ABE5FEE29A38 --lang=en-US --metrics-client-id=14916563-c75e-480b-b431-86b7db92b357 --extension-process --enable-offline-auto-reload --enable-offline-auto-reload-visible-only --blink-settings=disallowFetchForDocWrittenScriptsInMainFrame=false,disallowFetchForDocWrittenScriptsInMainFrameOnSlowConnections=false --enable-pinch --num-raster-threads=2 --enable-gpu-rasterization --enable-zero-copy --enable-gpu-memory-buffer-compositor-resources --enable-main-frame-before-activation --content-image-texture-target=0,0,3553;0,1,3553;0,2,3553;0,3,3553;0,4,3553;0,5,3553;0,6,3553;0,7,3553;0,8,3553;0,9,3553;0,10,34037;0,11,34037;0,12,34037;0,13,3553;0,14,3553;0,15,3553;1,0,3553;1,1,3553;1,2,3553;1,3,3553;1,4,3553;1,5,3553;1,6,3553;1,7,3553;1,8,3553;1,9,3553;1,10,34037;1,11,34037;1,12,34037;1,13,3553;1,14,3553;1,15,3553;2,0,3553;2,1,3553;2,2,3553;2,3,3553;2,4,3553;2,5,34037;2,6,3553;2,7,3553;2,8,3553;2,9,3553;2,10,3553;2,11,3553;2,12,34037;2,13,3553;2,14,34037;2,15,34037;3,0,3553;3,1,3553;3,2,3553;3,3,3553;3,4,3553;3,5,34037;3,6,3553;3,7,3553;3,8,3553;3,9,3553;3,10,3553;3,11,3553;3,12,34037;3,13,3553;3,14,34037;3,15,34037 --service-request-channel-token=12A8150786C5051C0C97ABE5FEE29A38 --renderer-client-id=4\nakrug            37205   0.0  0.0  2496128   2828   ??  Ss    6:13PM   0:00.11 \/System\/Library\/Frameworks\/VideoToolbox.framework\/Versions\/A\/XPCServices\/VTDecoderXPCService.xpc\/Contents\/MacOS\/VTDecoderXPCService\nakrug            37203   0.0  0.7  2871624 109736   ??  S     6:13PM   0:42.34 \/Applications\/Google Chrome.app\/Contents\/Versions\/56.0.2924.87\/Google Chrome Helper.app\/Contents\/MacOS\/Google Chrome Helper --type=gpu-process --enable-features=AutofillProfileCleanup<AutofillProfileCleanup,BlockSmallPluginContent<PluginPowerSaverTiny,EnableSyncClientToServerCompression<EnableSyncClientToServerCompression,*ExpectCTReporting<ExpectCTReporting,*NegotiateTLS13<TLS13Negotiation,ParseHTMLOnMainThread<ParseHTMLOnMainThread,*PersistentHistograms<PersistentHistograms,*PointerEvent<PointerEvent,PreferHtmlOverPlugins<Html5ByDefault,*PrioritySupportedRequestsDelayable<NetDelayableH2AndQuicRequests,SecurityChip<SecurityChip,SecurityWarningIconUpdate<SecurityWarningIconUpdate,SubresourceFilter<SubresourceFilter,*TranslateRankerLogging<TranslateRankerLogging,ViewsSimplifiedFullscreenUI<ViewsSimplifiedFullscreenUI --disable-features=DocumentWriteEvaluator<DisallowFetchForDocWrittenScriptsInMainFrame,SSLPostQuantumExperiment<SSLPostQuantum --force-fieldtrials=AppBannerTriggering\/site-engagement-eager\/AutofillProfileCleanup\/Enabled\/CaptivePortalInterstitial\/Enabled\/*ChromeChannelStable\/Enabled\/*ChromeSuggestionsTuning\/Default\/*ClientSideDetectionModel\/Model0\/DataReductionProxyUseQuic\/ControlForTcpLowat\/DisallowFetchForDocWrittenScriptsInMainFrame\/Control_20161208_Launch\/EnableSyncClientToServerCompression\/Enabled\/ExpectCTReporting\/ExpectCTReportingDisabled\/ExtensionDeveloperModeWarning\/Enabled\/ExtensionInstallVerification\/Enforce\/Html5ByDefault\/Enabled2\/InstanceID\/Enabled\/MarkNonSecureAs\/show-non-secure-passwords-cc-ui\/NetDelayableH2AndQuicRequests\/Default\/OfferUploadCreditCards\/Enabled\/OmniboxBundledExperimentV1\/StandardR7\/ParseHTMLOnMainThread\/Default\/PasswordBranding\/SmartLockBrandingSavePromptOnly\/*PasswordGeneration\/Disabled\/PasswordManagerSettingsMigration\/Enable\/*PersistentHistograms\/Default\/PluginPowerSaverTiny\/Enabled2\/*QUIC\/EnabledNoId\/ReportCertificateErrors\/ShowAndPossiblySend\/SHA1IdentityUIWarning\/Enabled\/SHA1ToolbarUIJanuary2016\/Warning\/SHA1ToolbarUIJanuary2017\/Error\/SSLCommonNameMismatchHandling\/Enabled\/SSLPostQuantum\/disabled\/*SafeBrowsingIncidentReportingService\/Default\/SafeBrowsingUnverifiedDownloads\/DisableByParameterMostSbTypes2\/SafeBrowsingV4LocalDatabaseManagerEnabled\/Default\/SaveAsMenuText\/default\/SecurityChip\/Enabled\/SecurityWarningIconUpdate\/Enabled2\/SignInPasswordPromo\/Enable3\/*SiteIsolationExtensions\/Enabled_100\/StrictSecureCookies\/Enabled\/SubresourceFilter\/EnabledForPhishingSites\/*TLS13Negotiation\/Default\/TranslateRankerLogging\/TranslateRankerLoggingDefault\/TranslateServerStudy\/Default\/*UMA-Dynamic-Uniformity-Trial\/Group3\/*UMA-Population-Restrict\/normal\/*UMA-Uniformity-Trial-1-Percent\/group_11\/*UMA-Uniformity-Trial-10-Percent\/group_05\/*UMA-Uniformity-Trial-100-Percent\/group_01\/*UMA-Uniformity-Trial-20-Percent\/group_03\/*UMA-Uniformity-Trial-5-Percent\/group_11\/*UMA-Uniformity-Trial-50-Percent\/default\/WebFontsInterventionV2\/Default\/ --metrics-client-id=14916563-c75e-480b-b431-86b7db92b357 --supports-dual-gpus=false --gpu-driver-bug-workarounds=0,1,10,23,25,35,38,39,45,51,59,61,62,63,64,66,70,71,73,81,82,83,86,88,89 --gpu-vendor-id=0x8086 --gpu-device-id=0x1927 --gpu-driver-vendor --gpu-driver-version --gpu-driver-date --gpu-active-vendor-id=0x8086 --gpu-active-device-id=0x1927 --metrics-client-id=14916563-c75e-480b-b431-86b7db92b357 --service-request-channel-token=AD4E87807C52375D52CAA7289C8548B5\nakrug            37201   0.0  0.0  2471052   2628   ??  S     6:13PM   0:00.02 \/Applications\/Google Chrome.app\/Contents\/Versions\/56.0.2924.87\/Google Chrome Framework.framework\/Helpers\/crashpad_handler --database=\/Users\/akrug\/Library\/Application Support\/Google\/Chrome\/Crashpad --url=https:\/\/clients2.google.com\/cr\/report --annotation=plat=OS X --annotation=prod=Chrome_Mac --annotation=ver=56.0.2924.87 --handshake-fd=7\n_gamecontrollerd 37199   0.0  0.0  2470772   3580   ??  Ss    6:13PM   0:03.20 \/usr\/libexec\/gamecontrollerd\nakrug            36981   0.0  0.1  2533100  10572   ??  S     4:08PM   0:00.37 \/System\/Library\/PrivateFrameworks\/UniversalAccess.framework\/Versions\/A\/Resources\/universalAccessAuthWarn.app\/Contents\/MacOS\/universalAccessAuthWarn launchd -s\nakrug            36930   0.0  0.1  2499632  17388   ??  Ss    4:01PM   0:00.22 \/System\/Library\/Frameworks\/Metal.framework\/Versions\/A\/XPCServices\/MTLCompilerService.xpc\/Contents\/MacOS\/MTLCompilerService\nakrug            10689   0.0  1.0  5622096 160580   ??  S     3:37PM   0:43.45 \/Applications\/FirefoxDeveloperEdition.app\/Contents\/MacOS\/plugin-container.app\/Contents\/MacOS\/plugin-container -childID 2 -isForBrowser -intPrefs 5:50|6:-1|18:0|28:1000|33:20|34:10|43:128|44:10000|48:0|50:400|51:1|52:0|53:0|58:0|59:120|60:120|133:2|134:1|147:5000|157:0|159:0|170:10000|195:24|196:32768|198:0|199:0|207:5|211:1048576|212:100|213:5000|215:600|226:1|241:60000| -boolPrefs 1:0|2:1|4:0|26:1|27:1|30:0|35:1|36:0|37:0|38:0|39:1|40:0|41:1|42:1|45:0|46:0|47:0|49:0|54:1|55:1|56:1|57:1|61:1|62:1|63:0|64:1|65:1|66:1|67:1|70:0|71:0|74:1|75:1|79:1|80:1|81:1|82:0|84:0|85:0|86:1|87:0|90:0|91:1|92:1|93:1|94:1|95:1|96:0|97:1|98:1|99:0|100:1|101:0|102:1|103:1|104:0|105:1|106:1|107:1|108:0|109:1|110:1|111:1|112:0|113:1|114:1|115:1|116:1|117:1|118:1|119:1|120:1|122:0|123:0|124:0|125:1|126:0|127:1|131:1|132:1|135:1|136:0|141:0|146:0|149:1|151:0|152:1|154:1|158:0|162:0|164:1|165:1|171:0|172:0|173:1|175:0|186:0|193:0|194:0|197:1|200:0|202:1|204:1|205:0|210:0|214:1|219:0|220:0|221:0|222:1|224:1|225:1|228:1|233:0|234:0|235:1|236:1|237:0|238:1|239:1|240:1|242:0|243:0|245:1|253:1|254:0|255:0|256:0|257:0| -stringPrefs 3:6:aurora|174:3:1.0|191:332: \\240\u00bc\u00bd\u00be\u01c3\u02d0\u0337\u0338\u0589\u058a\u05c3\u05f4^F^I^F^J\u066a\u06d4\u0701\u0702\u0703\u0704\u115f\u1160\u1735\\040^@\\040^A\\040^B\\040^C\\040^D\\040^E\\040^F\\040^G\\040^H\\040^I\\040^J\\040^K\\040^N\\040^O\u2010\u2019\u2024\u2027\\040-(\\040-)\\040-*\\040-+\\040-,\\040--\\040-.\\040-\/\u2039\u203a\u2041\u2044\u2052\\040-_\u2153\u2154\u2155\u2156\u2157\u2158\u2159\u215a\u215b\u215c\u215d\u215e\u215f\u2215\u2236\u23ae\u2571\u29f6\u29f8\u2afb\u2afd\u2ff0\u2ff1\u2ff2\u2ff3\u2ff4\u2ff5\u2ff6\u2ff7\u2ff8\u2ff9\u2ffa\u2ffb-0^@\u3002\u3014\u3015\u3033\u30a0\u3164-2^]-2^^\u33ae\u33af\u33c6-3M-_M-'M^IM-~^TM-~^U\ufe3f\ufe5d\ufe5eM-~M^?\uff0e\uff0f\uff61\uffa0M^?M-yM^?M-zM^?M-{\ufffc\ufffd|192:8:moderate|227:38:{5df6a0b3-4fcf-c34e-b0dc-fbdbff88d152}| -greomni \/Applications\/FirefoxDeveloperEdition.app\/Contents\/Resources\/omni.ja -appomni \/Applications\/FirefoxDeveloperEdition.app\/Contents\/Resources\/browser\/omni.ja -appdir \/Applications\/FirefoxDeveloperEdition.app\/Contents\/Resources\/browser -profile \/Users\/akrug\/Library\/Application Support\/Firefox\/Profiles\/jyemmr24.dev-edition-default 6919 gecko-crash-server-pipe.6919 org.mozilla.machname.2057285082 tab\nakrug            10677   0.0  0.1  2564344  16404   ??  S     3:35PM   0:01.21 \/System\/Library\/CoreServices\/NowPlayingTouchUI.app\/Contents\/MacOS\/NowPlayingTouchUI\nroot             10389   0.0  0.0  2470164   2340   ??  Ss    2:35PM   0:00.15 \/System\/Library\/PrivateFrameworks\/SystemAdministration.framework\/XPCServices\/writeconfig.xpc\/Contents\/MacOS\/writeconfig\nroot             10381   0.0  0.0  2471820   3576   ??  Ss    2:35PM   0:00.21 corestoragehelperd\nakrug            10074   0.0  0.1  2571084  16832   ??  S     2:32PM   0:00.44 \/System\/Library\/CoreServices\/OSDUIHelper.app\/Contents\/MacOS\/OSDUIHelper\nakrug             6955   0.0  0.0  2495756   3920   ??  Ss   Wed08AM   0:00.20 \/System\/Library\/Frameworks\/AudioToolbox.framework\/XPCServices\/com.apple.audio.ComponentHelper.xpc\/Contents\/MacOS\/com.apple.audio.ComponentHelper\nakrug             6954   0.0  0.0  2469896   3448   ??  Ss   Wed08AM   0:00.14 \/System\/Library\/Frameworks\/AudioToolbox.framework\/XPCServices\/com.apple.audio.SandboxHelper.xpc\/Contents\/MacOS\/com.apple.audio.SandboxHelper\nakrug             3493   0.0  0.0  2496944   4656   ??  Ss   Tue09PM   0:01.65 \/Library\/Frameworks\/iTunesLibrary.framework\/Versions\/A\/XPCServices\/com.apple.iTunesLibraryService.xpc\/Contents\/MacOS\/com.apple.iTunesLibraryService\nakrug             3487   0.0  0.0  2495400   5344   ??  Ss   Tue09PM   0:00.71 \/System\/Library\/PrivateFrameworks\/AssistantServices.framework\/Versions\/A\/XPCServices\/media-indexer.xpc\/Contents\/MacOS\/media-indexer\nroot              3486   0.0  0.0  2461744    788   ??  SNs  Tue09PM   0:00.01 \/usr\/libexec\/periodic-wrapper daily\nakrug             3240   0.0  0.0  2469692   3476   ??  S    Tue08PM   0:00.60 \/System\/Library\/CoreServices\/EscrowSecurityAlert.app\/Contents\/MacOS\/EscrowSecurityAlert\nakrug             2601   0.0  0.1  2535496  11828   ??  S    Tue03PM   0:01.78 \/System\/Library\/Frameworks\/LocalAuthentication.framework\/Support\/coreautha.bundle\/Contents\/MacOS\/coreautha\nroot              2597   0.0  0.0  2495924   2420   ??  Ss   Tue03PM   0:00.64 \/System\/Library\/PrivateFrameworks\/StreamingZip.framework\/Versions\/A\/XPCServices\/com.apple.StreamingUnzipService.xpc\/Contents\/MacOS\/com.apple.StreamingUnzipService\n_assetcache       2596   0.0  0.0  2497128   7088   ??  Ss   Tue03PM   0:03.47 \/System\/Library\/PrivateFrameworks\/AssetCacheServices.framework\/XPCServices\/AssetCacheLocatorService.xpc\/Contents\/MacOS\/AssetCacheLocatorService -d\nakrug             2592   0.0  0.0  2470484   3672   ??  S    Tue02PM   0:01.08 \/System\/Library\/PrivateFrameworks\/StorageManagement.framework\/Resources\/diskspaced\nroot              2488   0.0  0.0  2470688   4044   ??  Ss   Tue02PM   0:00.85 \/Library\/PrivilegedHelperTools\/com.sparklabs.ViscosityHelper\nakrug             2487   0.0  0.6  2708444  98472   ??  S    Tue02PM   0:29.93 \/Applications\/Viscosity.app\/Contents\/MacOS\/Viscosity\nakrug             2443   0.0  0.0  2478880   8184   ??  Ss   Tue01PM   0:01.03 \/System\/Library\/Frameworks\/Metal.framework\/Versions\/A\/XPCServices\/MTLCompilerService.xpc\/Contents\/MacOS\/MTLCompilerService\nakrug             2442   0.0  0.0  2470984   4372   ??  S    Tue01PM   0:00.65 \/System\/Library\/CoreServices\/rcd.app\/Contents\/MacOS\/rcd\nakrug             2440   0.0  0.0  2469976   2368   ??  S    Tue01PM   0:01.00 \/System\/Library\/Frameworks\/MediaAccessibility.framework\/Versions\/A\/XPCServices\/com.apple.accessibility.mediaaccessibilityd.xpc\/Contents\/MacOS\/com.apple.accessibility.mediaaccessibilityd\n_softwareupdate   2146   0.0  0.0  2496968   4368   ??  Ss   Tue01PM   0:01.96 \/System\/Library\/CoreServices\/Software Update.app\/Contents\/Resources\/softwareupdate_download_service\nakrug             2108   0.0  0.0  2471360   6424   ??  S    Tue01PM   0:01.07 \/usr\/libexec\/SafariPlugInUpdateNotifier\nroot              2076   0.0  0.0  2461300   1676   ??  Ss   Tue01PM   0:00.02 \/System\/Library\/PrivateFrameworks\/DiskImages.framework\/Resources\/hdiejectd\nroot              2072   0.0  0.1  2516120  24900   ??  Ss   Tue01PM   0:05.52 \/System\/Library\/PrivateFrameworks\/DiskImages.framework\/Resources\/diskimages-helper -uuid 22FCD621-6A85-4046-92AB-A59CC4304EE5 -post-exec 4\nroot              1512   0.0  0.1  2497880   8424   ??  Ss   Tue11AM   0:01.46 \/usr\/libexec\/syspolicyd\nakrug             1159   0.0  0.0  2445828   2172   ??  S    Tue10AM   0:00.03 \/usr\/bin\/ssh-agent -l\nakrug              936   0.0  0.0  2496396   7016   ??  S    Tue10AM   0:01.17 \/System\/Library\/Frameworks\/ApplicationServices.framework\/Frameworks\/PrintCore.framework\/Versions\/A\/printtool agent\nakrug              903   0.0  0.1  2499632  10924   ??  Ss   Tue10AM   0:02.01 \/System\/Library\/PrivateFrameworks\/CommerceKit.framework\/Versions\/A\/XPCServices\/com.apple.CommerceKit.TransactionService.xpc\/Contents\/MacOS\/com.apple.CommerceKit.TransactionService\nakrug              851   0.0  0.0  2502492   5524   ??  S    Tue09AM   0:01.21 \/System\/Library\/PrivateFrameworks\/PhotoAnalysis.framework\/Versions\/A\/Support\/photoanalysisd\nakrug              738   0.0  0.0  2471068   3912   ??  S    Tue08AM   0:00.76 \/usr\/libexec\/USBAgent\nakrug              728   0.0  0.0  2469632   2908   ??  S    Tue08AM   0:00.04 \/System\/Library\/Frameworks\/ApplicationServices.framework\/Versions\/A\/Frameworks\/HIServices.framework\/Versions\/A\/XPCServices\/com.apple.hiservices-xpcservice.xpc\/Contents\/MacOS\/com.apple.hiservices-xpcservice\nroot               727   0.0  0.0  2461160   2456   ??  Ss   Tue08AM   0:00.01 \/System\/Library\/Frameworks\/CoreMediaIO.framework\/Versions\/A\/XPCServices\/com.apple.cmio.registerassistantservice.xpc\/Contents\/MacOS\/com.apple.cmio.registerassistantservice\nakrug              725   0.0  0.0  2495648   5028   ??  S    Tue08AM   0:01.56 \/System\/Library\/CoreServices\/ScopedBookmarkAgent\nroot               702   0.0  0.0  2469936   1816   ??  Ss   Tue08AM   0:00.68 \/System\/Library\/PrivateFrameworks\/InstallerDiagnostics.framework\/Versions\/A\/Resources\/installerdiagd\nakrug              676   0.0  0.0  2470044   2440   ??  S    Tue08AM   0:00.72 \/System\/Library\/PrivateFrameworks\/KerberosHelper\/Helpers\/DiskUnmountWatcher\nakrug              639   0.0  0.0  2495324   3408   ??  S    Tue08AM   0:01.00 \/System\/Library\/Frameworks\/CoreServices.framework\/Versions\/A\/Frameworks\/DictionaryServices.framework\/Versions\/A\/XPCServices\/com.apple.DictionaryServiceHelper.xpc\/Contents\/MacOS\/com.apple.DictionaryServiceHelper\nakrug              636   0.0  0.0  2496652   7280   ??  Ss   Tue08AM   0:01.12 \/System\/Library\/PrivateFrameworks\/SafariShared.framework\/Versions\/A\/XPCServices\/com.apple.Safari.History.xpc\/Contents\/MacOS\/com.apple.Safari.History\nroot               633   0.0  0.0  2470084   3764   ??  Ss   Tue08AM   0:00.09 \/System\/Library\/CoreServices\/SubmitDiagInfo server-init\nakrug              601   0.0  0.0  2495620   5328   ??  S    Tue08AM   0:01.72 \/System\/Library\/Frameworks\/CoreServices.framework\/Frameworks\/Metadata.framework\/Versions\/A\/Support\/mdwrite\nakrug              600   0.0  0.0  2497096   7160   ??  S    Tue08AM   0:02.57 \/System\/Library\/Frameworks\/CoreServices.framework\/Frameworks\/Metadata.framework\/Versions\/A\/Support\/mdworker -s mdworker-sizing -c MDSSizingWorker -m com.apple.mdworker.sizing\n_spotlight         599   0.0  0.0  2498380   7144   ??  S    Tue08AM   0:30.98 \/System\/Library\/Frameworks\/CoreServices.framework\/Frameworks\/Metadata.framework\/Versions\/A\/Support\/mdworker -s mdworker-sizing -c MDSSizingWorker -m com.apple.mdworker.sizing\nakrug              597   0.0  0.0  2498972   3892   ??  Ss   Tue08AM   0:01.03 \/System\/Library\/PrivateFrameworks\/CommerceKit.framework\/Versions\/A\/XPCServices\/com.apple.CommerceKit.TransactionService.xpc\/Contents\/MacOS\/com.apple.CommerceKit.TransactionService\n_spotlight         590   0.0  0.0  2469460   1792   ??  S    Tue08AM   0:02.28 \/usr\/sbin\/distnoted agent\nakrug              585   0.0  0.1  2540844  10812   ??  S    Tue08AM   0:02.02 \/System\/Library\/PrivateFrameworks\/CoreSuggestions.framework\/Versions\/A\/Support\/suggestd\n_spotlight         578   0.0  0.0  2498100   6660   ??  S    Tue08AM   0:11.15 \/usr\/libexec\/trustd --agent\nakrug              572   0.0  0.2  3675692  35552   ??  S    Tue08AM   1:49.44 \/Applications\/Flux.app\/Contents\/MacOS\/Flux\nakrug              565   0.0  0.1  2533104  10764   ??  S    Tue08AM   0:01.71 \/System\/Library\/PrivateFrameworks\/CommerceKit.framework\/Resources\/LaterAgent.app\/Contents\/MacOS\/LaterAgent\nroot               564   0.0  0.0  2469648   2992   ??  Ss   Tue08AM   0:00.58 \/System\/Library\/PrivateFrameworks\/CommerceKit.framework\/Versions\/A\/Resources\/storeinstalld\nakrug              563   0.0  0.0  2496172   3768   ??  S    Tue08AM   0:00.60 \/System\/Library\/PrivateFrameworks\/CommerceKit.framework\/Versions\/A\/Resources\/storelegacy\nakrug              561   0.0  0.0  2446284   2088   ??  S    Tue08AM   0:01.76 \/System\/Library\/Frameworks\/CoreServices.framework\/Frameworks\/Metadata.framework\/Versions\/A\/Support\/mdflagwriter\nroot               560   0.0  0.0  2470860   2124   ??  S    Tue08AM   0:00.04 \/System\/Library\/Frameworks\/CoreServices.framework\/Frameworks\/Metadata.framework\/Versions\/A\/Support\/mdflagwriter\nroot               546   0.0  0.0  2497316   6336   ??  Ss   Tue08AM   0:08.53 \/usr\/libexec\/wifivelocityd\nakrug              545   0.0  0.0  2471504   7632   ??  S    Tue08AM   0:08.24 \/usr\/libexec\/WiFiVelocityAgent\nakrug              540   0.0  0.0  2470828   4836   ??  S    Tue08AM   0:00.64 \/System\/Library\/CoreServices\/Software Update.app\/Contents\/Resources\/softwareupdate_notify_agent\nakrug              536   0.0  0.0  2473176    856   ??  Ss   Tue08AM   0:06.57 \/usr\/local\/MacGPG2\/bin\/gpg-agent --daemon\n_nsurlstoraged     513   0.0  0.0  2470012   4412   ??  Ss   Tue08AM   0:00.69 \/usr\/libexec\/nsurlstoraged\nakrug              499   0.0  0.0  2434836    680   ??  S    Tue08AM   0:00.00 sleep 31536000\nakrug              492   0.0  0.1  2472720  12696   ??  S    Tue08AM   0:02.85 \/System\/Library\/PrivateFrameworks\/PrintingPrivate.framework\/Versions\/A\/PrintUITool\nakrug              483   0.0  0.0  2496012   6360   ??  S    Tue08AM   0:03.37 \/System\/Library\/CoreServices\/diagnostics_agent\nakrug              482   0.0  0.1  2530468   8860   ??  S    Tue08AM   0:04.67 \/System\/Library\/CoreServices\/WiFiAgent.app\/Contents\/MacOS\/WiFiAgent\nakrug              480   0.0  0.1  2542116  10492   ??  S    Tue08AM   0:02.31 \/System\/Library\/PrivateFrameworks\/Noticeboard.framework\/Versions\/A\/Resources\/nbagent.app\/Contents\/MacOS\/nbagent\nakrug              478   0.0  0.0  2496280   7076   ??  S    Tue08AM   0:09.40 \/System\/Library\/CoreServices\/cloudpaird\nakrug              477   0.0  0.1  2530020  10376   ??  S    Tue08AM   0:02.72 \/System\/Library\/CoreServices\/AirPlayUIAgent.app\/Contents\/MacOS\/AirPlayUIAgent --launchd\nakrug              476   0.0  0.0  2443632   1100   ??  S    Tue08AM   0:00.01 \/bin\/bash \/usr\/local\/MacGPG2\/libexec\/shutdown-gpg-agent\nakrug              475   0.0  0.2  2564104  38900   ??  S    Tue08AM   0:38.60 \/System\/Library\/CoreServices\/PowerChime.app\/Contents\/MacOS\/PowerChime\nakrug              472   0.0  0.0  2496132   8084   ??  S    Tue08AM   0:01.45 \/System\/Library\/Image Capture\/Support\/icdd\nakrug              469   0.0  0.3  2721812  43968   ??  S    Tue08AM   0:18.96 \/System\/Library\/CoreServices\/NotificationCenter.app\/Contents\/MacOS\/NotificationCenter\nakrug              465   0.0  0.0  2495068   3380   ??  S    Tue08AM   0:01.14 \/System\/Library\/CoreServices\/SocialPushAgent.app\/Contents\/MacOS\/SocialPushAgent\nakrug              462   0.0  0.0  2495884   3992   ??  S    Tue08AM   0:00.99 \/usr\/libexec\/spindump_agent\nakrug              459   0.0  0.0  2517220   7716   ??  S    Tue08AM   0:01.47 \/System\/Library\/CoreServices\/FolderActionsDispatcher.app\/Contents\/MacOS\/FolderActionsDispatcher\nakrug              458   0.0  0.0  2496988   6112   ??  Ss   Tue08AM   0:01.94 \/Library\/Frameworks\/iTunesLibrary.framework\/Versions\/A\/XPCServices\/com.apple.iTunesLibraryService.xpc\/Contents\/MacOS\/com.apple.iTunesLibraryService\n_applepay          456   0.0  0.0  2496076   4008   ??  Ss   Tue08AM   0:02.29 \/usr\/libexec\/seld\nakrug              455   0.0  0.0  2461276   1484   ??  Ss   Tue08AM   0:00.01 \/System\/Library\/PrivateFrameworks\/IMFoundation.framework\/XPCServices\/IMRemoteURLConnectionAgent.xpc\/Contents\/MacOS\/IMRemoteURLConnectionAgent\nakrug              446   0.0  0.3  2706996  47268   ??  S    Tue08AM   0:03.73 \/System\/Library\/Services\/AppleSpell.service\/Contents\/MacOS\/AppleSpell -psn_0_147492\nakrug              444   0.0  0.2  2504768  27404   ??  S    Tue08AM   0:16.11 \/System\/Library\/PrivateFrameworks\/AssistantServices.framework\/assistant_service\nakrug              443   0.0  0.0  2469448   2616   ??  S    Tue08AM   0:01.08 \/System\/Library\/PrivateFrameworks\/MediaRemote.framework\/Support\/mediaremoteagent\nakrug              442   0.0  0.0  2496104   6728   ??  Ss   Tue08AM   0:03.70 \/System\/Library\/PrivateFrameworks\/IMFoundation.framework\/XPCServices\/IMRemoteURLConnectionAgent.xpc\/Contents\/MacOS\/IMRemoteURLConnectionAgent\nakrug              439   0.0  0.1  2533368  12792   ??  Ss   Tue08AM   0:01.58 \/System\/Library\/CoreServices\/ControlStrip.app\/Contents\/XPCServices\/com.apple.DFRSystemExtra.InputMenu.xpc\/Contents\/MacOS\/com.apple.DFRSystemExtra.InputMenu\nakrug              438   0.0  0.0  2496988   6168   ??  Ss   Tue08AM   0:01.53 \/Library\/Frameworks\/iTunesLibrary.framework\/Versions\/A\/XPCServices\/com.apple.iTunesLibraryService.xpc\/Contents\/MacOS\/com.apple.iTunesLibraryService\nakrug              436   0.0  0.2  2512648  29664   ??  S    Tue08AM   0:15.84 \/System\/Library\/PrivateFrameworks\/AssistantServices.framework\/assistantd\nakrug              435   0.0  0.0  2473660   3876   ??  Ss   Tue08AM   0:00.98 \/System\/Library\/PrivateFrameworks\/CommerceKit.framework\/Versions\/A\/XPCServices\/com.apple.CommerceKit.TransactionService.xpc\/Contents\/MacOS\/com.apple.CommerceKit.TransactionService\nakrug              434   0.0  0.0  2500160   7984   ??  S    Tue08AM   0:01.06 \/System\/Library\/PrivateFrameworks\/PhotoLibraryPrivate.framework\/Versions\/A\/Support\/photolibraryd\nakrug              405   0.0  0.0  2495676   4732   ??  S    Tue08AM   0:01.21 \/System\/Library\/CoreServices\/pbs\nakrug              404   0.0  0.0  2495588   6888   ??  Ss   Tue08AM   0:14.51 \/System\/Library\/PrivateFrameworks\/CoreWLANKit.framework\/Versions\/A\/XPCServices\/WiFiProxy.xpc\/Contents\/MacOS\/WiFiProxy\nakrug              402   0.0  0.0  2495736   4972   ??  S    Tue08AM   0:00.60 \/System\/Library\/PrivateFrameworks\/CharacterPicker.framework\/Versions\/A\/XPCServices\/com.apple.CharacterPicker.FileService.xpc\/Contents\/MacOS\/com.apple.CharacterPicker.FileService\nakrug              401   0.0  0.1  2552692  14592   ??  Ss   Tue08AM   0:24.73 \/System\/Library\/Input Methods\/EmojiFunctionRowIM.app\/Contents\/PlugIns\/EmojiFunctionRowIM_Extension.appex\/Contents\/MacOS\/EmojiFunctionRowIM_Extension\nakrug              400   0.0  0.1  2530608  11148   ??  Ss   Tue08AM   0:05.26 \/System\/Library\/Input Methods\/PressAndHold.app\/Contents\/PlugIns\/PAH_Extension.appex\/Contents\/MacOS\/PAH_Extension\nakrug              399   0.0  0.0  2513800   7236   ??  S    Tue08AM   0:01.29 \/System\/Library\/Frameworks\/InputMethodKit.framework\/Resources\/imklaunchagent\nakrug              398   0.0  0.1  2498316  10480   ??  S    Tue08AM   0:02.55 \/System\/Library\/PrivateFrameworks\/CommerceKit.framework\/Versions\/A\/Resources\/storeassetd\nroot               397   0.0  0.0  2453828   1852   ??  Ss   Tue08AM   0:01.18 \/usr\/libexec\/watchdogd\nakrug              395   0.0  0.5  3491316  83704   ??  S    Tue08AM   0:21.37 \/System\/Library\/CoreServices\/Spotlight.app\/Contents\/MacOS\/Spotlight\nakrug              389   0.0  0.0  2495344   5492   ??  S    Tue08AM   0:01.08 \/System\/Library\/PrivateFrameworks\/CallHistory.framework\/Support\/CallHistoryPluginHelper\nakrug              388   0.0  0.1  2513056  15520   ??  S    Tue08AM   0:01.47 \/System\/Library\/PrivateFrameworks\/MessagesKit.framework\/Resources\/soagent.app\/Contents\/MacOS\/soagent\nroot               386   0.0  0.6  2589072 107908   ??  Ss   Tue08AM   0:20.22 \/usr\/sbin\/spindump\nakrug              380   0.0  0.0  2496408   6008   ??  S    Tue08AM   0:01.25 \/usr\/libexec\/swcd\nroot               379   0.0  0.0  2469840   3668   ??  Ss   Tue08AM   0:00.68 \/System\/Library\/CoreServices\/sharedfilelistd --enable-legacy-services\nakrug              378   0.0  0.0  2496720   6108   ??  S    Tue08AM   0:01.36 \/System\/Library\/Frameworks\/CryptoTokenKit.framework\/ctkd -tw\nroot               377   0.0  0.0  2496904   4632   ??  Ss   Tue08AM   0:02.49 \/usr\/libexec\/findmydeviced\nakrug              376   0.0  0.0  2469708   3144   ??  S    Tue08AM   0:00.03 \/System\/Library\/Frameworks\/CryptoTokenKit.framework\/ctkahp.bundle\/Contents\/MacOS\/ctkahp\nakrug              375   0.0  0.1  2503416  14920   ??  S    Tue08AM   1:27.68 \/usr\/libexec\/sharingd\nakrug              371   0.0  0.1  2535112  20520   ??  Ss   Tue08AM   0:01.61 \/System\/Library\/CoreServices\/Dock.app\/Contents\/XPCServices\/com.apple.dock.extra.xpc\/Contents\/MacOS\/com.apple.dock.extra\nakrug              368   0.0  0.1  2499112  11832   ??  S    Tue08AM   0:02.42 \/System\/Library\/PrivateFrameworks\/CommerceKit.framework\/Versions\/A\/Resources\/storeaccountd\nakrug              365   0.0  0.0  2497676   8192   ??  S    Tue08AM   0:07.44 \/System\/Library\/PrivateFrameworks\/UserActivity.framework\/Agents\/useractivityd\nakrug              364   0.0  0.1  2501660  14036   ??  Ss   Tue08AM   0:16.67 \/System\/Library\/PrivateFrameworks\/CalendarNotification.framework\/Versions\/A\/XPCServices\/CalNCService.xpc\/Contents\/MacOS\/CalNCService\nakrug              363   0.0  0.2  2553216  36912   ??  S    Tue08AM   0:02.23 \/System\/Library\/CoreServices\/iconservicesagent\nakrug              360   0.0  0.1  2497940  12932   ??  S    Tue08AM   0:38.07 \/System\/Library\/PrivateFrameworks\/GeoServices.framework\/Versions\/A\/XPCServices\/com.apple.geod.xpc\/Contents\/MacOS\/com.apple.geod\nakrug              358   0.0  0.1  2501408  14908   ??  S    Tue08AM   0:08.53 \/System\/Library\/PrivateFrameworks\/CalendarAgent.framework\/Executables\/CalendarAgent\nakrug              357   0.0  0.1  2516292  16228   ??  S    Tue08AM   0:04.91 \/System\/Library\/PrivateFrameworks\/CoreParsec.framework\/parsecd\nakrug              355   0.0  0.0  2497172   5688   ??  S    Tue08AM   0:02.99 \/usr\/libexec\/networkserviceproxy\nakrug              352   0.0  0.0  2495108   6612   ??  S    Tue08AM   0:01.97 \/System\/Library\/PrivateFrameworks\/CloudPhotoServices.framework\/Versions\/A\/Frameworks\/CloudPhotosConfigurationXPC.framework\/Versions\/A\/XPCServices\/com.apple.CloudPhotosConfiguration.xpc\/Contents\/MacOS\/com.apple.CloudPhotosConfiguration\nroot               350   0.0  0.0  2473324   3868   ??  Ss   Tue08AM   0:00.72 \/usr\/sbin\/filecoordinationd\nakrug              349   0.0  0.1  2496744   8420   ??  S    Tue08AM   0:06.04 \/usr\/libexec\/nsurlsessiond\nakrug              344   0.0  0.1  2497212   9908   ??  S    Tue08AM   0:04.26 \/usr\/sbin\/usernoted\nakrug              343   0.0  0.1  2496640   9640   ??  S    Tue08AM   0:06.00 \/System\/Library\/PrivateFrameworks\/CloudKitDaemon.framework\/Support\/cloudd\n_applepay          339   0.0  0.0  2497036   4612   ??  Ss   Tue08AM   0:01.09 \/usr\/libexec\/nfcd\nakrug              338   0.0  0.0  2469780   4444   ??  S    Tue08AM   0:01.07 \/System\/Library\/Frameworks\/Security.framework\/Versions\/A\/Resources\/IDSKeychainSyncingProxy.bundle\/Contents\/MacOS\/IDSKeychainSyncingProxy\nakrug              337   0.0  0.0  2469676   3096   ??  S    Tue08AM   0:00.62 \/System\/Library\/Frameworks\/Security.framework\/Versions\/A\/Resources\/CloudKeychainProxy.bundle\/Contents\/MacOS\/CloudKeychainProxy\nakrug              336   0.0  0.1  2497976   9060   ??  S    Tue08AM   0:04.95 \/usr\/libexec\/nsurlstoraged\nakrug              335   0.0  0.1  2498540  10480   ??  S    Tue08AM   0:02.98 \/System\/Library\/PrivateFrameworks\/PassKitCore.framework\/passd\nakrug              334   0.0  0.0  2496620   8220   ??  S    Tue08AM   0:01.44 \/usr\/libexec\/fmfd\nakrug              333   0.0  0.1  2500228   9504   ??  S    Tue08AM   0:02.11 \/System\/Library\/PrivateFrameworks\/AuthKit.framework\/Versions\/A\/Support\/akd\nakrug              332   0.0  0.0  2499620   6520   ??  S    Tue08AM   0:01.26 \/System\/Library\/PrivateFrameworks\/CallHistory.framework\/Support\/CallHistorySyncHelper\nakrug              331   0.0  0.0  2495084   4292   ??  S    Tue08AM   0:01.13 \/System\/Library\/PrivateFrameworks\/AskPermission.framework\/Versions\/A\/Resources\/askpermissiond\nakrug              330   0.0  0.0  2500908   8156   ??  S    Tue08AM   0:06.05 \/usr\/libexec\/keyboardservicesd\nakrug              328   0.0  0.0  2497452   7316   ??  S    Tue08AM   0:02.37 \/System\/Library\/CoreServices\/AppleIDAuthAgent\n_captiveagent      324   0.0  0.0  2471728   5320   ??  Ss   Tue08AM   0:01.90 \/usr\/libexec\/captiveagent\nakrug              323   0.0  0.1  2496112   8480   ??  S    Tue08AM   0:02.05 \/System\/Library\/CoreServices\/mapspushd\nakrug              318   0.0  0.1  2497096   8496   ??  S    Tue08AM   0:02.64 \/usr\/libexec\/secinitd\nroot               317   0.0  0.0  2499784   6296   ??  Ss   Tue08AM   0:00.65 \/System\/Library\/PrivateFrameworks\/TCC.framework\/Resources\/tccd system\nroot               315   0.0  0.0  2496424   5196   ??  Ss   Tue08AM   0:51.31 \/usr\/sbin\/WirelessRadioManagerd\nroot               314   0.0  0.0  2519644   4976   ??  Ss   Tue08AM   0:04.46 \/System\/Library\/PrivateFrameworks\/PackageKit.framework\/Resources\/system_installd\nakrug              313   0.0  0.0  2495124   3484   ??  S    Tue08AM   0:00.63 \/System\/Library\/PrivateFrameworks\/QuickLookThumbnailing.framework\/Support\/com.apple.quicklook.ThumbnailsAgent\nakrug              312   0.0  0.0  2494756   4212   ??  S    Tue08AM   0:01.09 \/System\/Library\/PrivateFrameworks\/GeoServices.framework\/geodMachServiceBridge\nakrug              311   0.0  0.0  2498404   6644   ??  S    Tue08AM   0:00.67 \/System\/Library\/PrivateFrameworks\/CommerceKit.framework\/Versions\/A\/Resources\/storedownloadd\nakrug              310   0.0  0.2  2539116  25728   ??  S    Tue08AM   0:04.02 \/System\/Library\/CoreServices\/cloudphotosd.app\/Contents\/MacOS\/cloudphotosd\nroot               309   0.0  0.2  2517276  25944   ??  Ss   Tue08AM   0:01.86 \/System\/Library\/PrivateFrameworks\/PackageKit.framework\/Resources\/installd\nroot               308   0.0  0.0  2470444   5172   ??  Ss   Tue08AM   0:00.96 \/System\/Library\/CoreServices\/backupd.bundle\/Contents\/Resources\/TMCacheDelete\nakrug              307   0.0  0.0  2469676   4552   ??  S    Tue08AM   0:01.30 \/System\/Library\/Frameworks\/AddressBook.framework\/Executables\/ContactsAccountsService\nakrug              306   0.0  0.0  2495720   6640   ??  S    Tue08AM   0:01.39 \/System\/Library\/PrivateFrameworks\/IMDPersistence.framework\/XPCServices\/IMDPersistenceAgent.xpc\/Contents\/MacOS\/IMDPersistenceAgent\nakrug              305   0.0  0.0  2495424   6980   ??  S    Tue08AM   0:02.12 \/usr\/libexec\/pkd\nakrug              304   0.0  0.0  2497008   6884   ??  S    Tue08AM   0:01.60 \/System\/Library\/PrivateFrameworks\/CacheDelete.framework\/deleted\nakrug              303   0.0  0.0  2496824   7908   ??  S    Tue08AM   0:01.85 \/System\/Library\/PrivateFrameworks\/TCC.framework\/Resources\/tccd\nakrug              302   0.0  0.0  2497348   8152   ??  S    Tue08AM   0:04.07 \/System\/Library\/PrivateFrameworks\/IMCore.framework\/imagent.app\/Contents\/MacOS\/imagent\nakrug              301   0.0  0.1  2506884  14820   ??  S    Tue08AM   0:11.29 \/System\/Library\/PrivateFrameworks\/IDS.framework\/identityservicesd.app\/Contents\/MacOS\/identityservicesd\nakrug              300   0.0  0.0  2499744   5984   ??  S    Tue08AM   0:01.64 \/System\/Library\/Frameworks\/Accounts.framework\/Versions\/A\/Support\/accountsd\nakrug              298   0.0  0.0  2496136   6768   ??  S    Tue08AM   0:08.62 \/System\/Library\/PrivateFrameworks\/CloudDocsDaemon.framework\/Versions\/A\/Support\/bird\nakrug              297   0.0  0.1  2502960  16580   ??  S    Tue08AM   0:09.38 \/System\/Library\/PrivateFrameworks\/TelephonyUtilities.framework\/callservicesd\nakrug              295   0.0  0.0  2486960   5592   ??  S    Tue08AM   0:00.51 \/usr\/libexec\/pboard\nakrug              293   0.0  0.0  2497324   5112   ??  S    Tue08AM   0:01.29 \/usr\/libexec\/secd\nakrug              291   0.0  1.2  2985284 196164   ??  S    Tue08AM   2:01.71 \/System\/Library\/CoreServices\/Finder.app\/Contents\/MacOS\/Finder\nakrug              290   0.0  0.3  2603300  48464   ??  S    Tue08AM   2:28.79 \/System\/Library\/CoreServices\/SystemUIServer.app\/Contents\/MacOS\/SystemUIServer\nakrug              283   0.0  0.1  2529408  11316   ??  S    Tue08AM   1:07.40 \/System\/Library\/Frameworks\/ApplicationServices.framework\/Frameworks\/ATS.framework\/Support\/fontd\nakrug              282   0.0  0.0  2497120   7172   ??  S    Tue08AM   0:02.75 \/System\/Library\/CoreServices\/sharedfilelistd\nakrug              281   0.0  0.2  2584792  25780   ??  S    Tue08AM   0:06.66 \/System\/Library\/CoreServices\/ControlStrip.app\/Contents\/MacOS\/ControlStrip\nakrug              279   0.0  0.1  2500356   9120   ??  S    Tue08AM   0:40.80 \/usr\/libexec\/trustd --agent\nakrug              278   0.0  0.1  2499424  11112   ??  S    Tue08AM   0:09.92 \/usr\/libexec\/lsd\nakrug              277   0.0  0.1  2518904  24976   ??  S    Tue08AM   0:53.32 \/System\/Library\/Frameworks\/CoreTelephony.framework\/Support\/CommCenter -L\nakrug              276   0.0  0.0  2495428   3880   ??  S    Tue08AM   0:01.03 \/System\/Library\/Frameworks\/LocalAuthentication.framework\/Support\/coreauthd\nakrug              275   0.0  0.0  2470124   3512   ??  S    Tue08AM   0:32.93 \/usr\/sbin\/cfprefsd agent\nakrug              274   0.0  0.0  2509120   7008   ??  S    Tue08AM   0:05.12 \/System\/Library\/CoreServices\/ControlStrip.app\/Contents\/MacOS\/TouchBarAgent\nakrug              272   0.0  0.0  2469984   6072   ??  S    Tue08AM   0:45.70 \/usr\/sbin\/distnoted agent\nakrug              270   0.0  0.1  2497384  17072   ??  S    Tue08AM   0:41.85 \/usr\/libexec\/UserEventAgent (Aqua)\nroot               266   0.0  0.0  2451760   1184   ??  S    Tue08AM   0:00.00 \/usr\/libexec\/ioupsd\nroot               265   0.0  0.0  2469724   3140   ??  Ss   Tue08AM   0:11.42 sysmond\nroot               262   0.0  0.0  2469896   3412   ??  Ss   Tue08AM   0:00.62 \/System\/Library\/Frameworks\/AudioToolbox.framework\/XPCServices\/com.apple.audio.SandboxHelper.xpc\/Contents\/MacOS\/com.apple.audio.SandboxHelper\nroot               261   0.0  0.0  2500104   6832   ??  Ss   Tue08AM   0:03.43 \/usr\/sbin\/systemsoundserverd\nroot               258   0.0  0.0  2471164   2584   ??  Ss   Tue08AM   0:00.02 \/usr\/libexec\/securityd_service\nroot               256   0.0  0.0  2495592   7544   ??  Ss   Tue08AM   0:01.50 \/System\/Library\/Frameworks\/LocalAuthentication.framework\/Support\/coreauthd\nroot               254   0.0  0.0  2469736   2648   ??  Ss   Tue08AM   0:00.96 \/usr\/libexec\/diagnosticd\nroot               252   0.0  0.0  2501408   5092   ??  Ss   Tue08AM   0:01.49 \/System\/Library\/PrivateFrameworks\/SoftwareUpdate.framework\/Resources\/suhelperd\nroot               243   0.0  0.0  2470248   2232   ??  Ss   Tue08AM   0:00.75 \/System\/Library\/Frameworks\/GSS.framework\/Helpers\/com.apple.GSSCred\nroot               240   0.0  0.0  2469984   2528   ??  Ss   Tue08AM   0:00.63 \/System\/Library\/PrivateFrameworks\/AccountPolicy.framework\/XPCServices\/com.apple.AccountPolicyHelper.xpc\/Contents\/MacOS\/com.apple.AccountPolicyHelper\nroot               236   0.0  0.0  2496888   7260   ??  Ss   Tue08AM   0:01.46 \/usr\/libexec\/secinitd\nroot               235   0.0  0.0  2469708   2808   ??  Ss   Tue08AM   0:00.03 \/System\/Library\/Frameworks\/CryptoTokenKit.framework\/ctkahp.bundle\/Contents\/MacOS\/ctkahp -d\nroot               229   0.0  0.0  2466380   3444   ??  Ss   Tue08AM   0:01.02 \/System\/Library\/CoreServices\/ControlStrip.app\/Contents\/MacOS\/TouchBarUserDevice\nroot               224   0.0  0.0  2471696   5048   ??  Ss   Tue08AM   0:02.52 \/System\/Library\/Frameworks\/Security.framework\/Versions\/A\/XPCServices\/com.apple.CodeSigningHelper.xpc\/Contents\/MacOS\/com.apple.CodeSigningHelper\nroot               211   0.0  0.0  2505024   2952   ??  Ss   Tue08AM   0:00.10 \/System\/Library\/Frameworks\/OpenGL.framework\/Versions\/A\/Libraries\/CVMServer\nroot               210   0.0  0.0  2499720   7940   ??  Ss   Tue08AM   2:12.58 \/System\/Library\/PrivateFrameworks\/StorageKit.framework\/Resources\/storagekitd\nroot               209   0.0  0.1  2510740  16836   ??  Ss   Tue08AM   0:01.04 \/System\/Library\/PrivateFrameworks\/EmbeddedOSInstall.framework\/Versions\/A\/XPCServices\/EmbeddedOSInstallService.xpc\/Contents\/MacOS\/EmbeddedOSInstallService\nroot               205   0.0  0.0  2496100   4820   ??  Ss   Tue08AM   2:34.52 \/System\/Library\/PrivateFrameworks\/AmbientDisplay.framework\/Versions\/A\/XPCServices\/com.apple.AmbientDisplayAgent.xpc\/Contents\/MacOS\/com.apple.AmbientDisplayAgent\n_softwareupdate    204   0.0  4.4  5817868 731768   ??  Ss   Tue08AM   2:39.04 \/System\/Library\/CoreServices\/Software Update.app\/Contents\/Resources\/softwareupdated\nroot               202   0.0  0.0  2494772   3672   ??  Ss   Tue08AM   0:01.26 \/usr\/libexec\/biokitaggdd\n_networkd          201   0.0  0.1  2507012  10056   ??  Ss   Tue08AM   1:50.41 \/usr\/libexec\/symptomsd\nroot               200   0.0  0.0  2498324   7756   ??  Ss   Tue08AM   0:29.47 \/usr\/libexec\/biometrickitd --launchd\nroot               199   0.0  0.0  2500532   6772   ??  Ss   Tue08AM   2:48.60 \/System\/Library\/Frameworks\/CoreMediaIO.framework\/Resources\/VDC.plugin\/Contents\/Resources\/VDCAssistant\nroot               198   0.0  0.0  2469440   2236   ??  Ss   Tue08AM   0:05.44 \/usr\/libexec\/eoshostd\nroot               197   0.0  0.0  2471664   5280   ??  Ss   Tue08AM   3:35.67 \/System\/Library\/CryptoTokenKit\/com.apple.ifdreader.slotd\/Contents\/MacOS\/com.apple.ifdreader\nroot               196   0.0  0.0  2469660   2716   ??  Ss   Tue08AM   0:01.51 \/usr\/libexec\/thermald\nroot               195   0.0  0.0  2496284   5988   ??  Ss   Tue08AM   0:09.18 \/usr\/libexec\/usbd\nroot               194   0.0  0.0  2470984   2888   ??  Ss   Tue08AM   0:00.65 \/usr\/libexec\/xartstorageremoted\nroot               192   0.0  0.0  2470540   4200   ??  Ss   Tue08AM   0:02.98 \/usr\/libexec\/corestoraged\nroot               191   0.0  0.0  2496796   7244   ??  Ss   Tue08AM   0:14.22 \/usr\/libexec\/ApplicationFirewall\/socketfilterfw\nroot               190   0.0  0.0  2499500   6100   ??  Ss   Tue08AM   0:01.72 \/usr\/libexec\/nehelper\nroot               189   0.0  0.0  2473040   3152   ??  Ss   Tue08AM   3:48.48 \/usr\/sbin\/ntpd -c \/private\/etc\/ntp-restrict.conf -n -g -p \/var\/run\/ntpd.pid -f \/var\/db\/ntp.drift\n_nsurlsessiond     188   0.0  0.0  2496984   8296   ??  Ss   Tue08AM   0:05.81 \/usr\/libexec\/nsurlsessiond --privileged\nroot               187   0.0  0.0  2495856   3028   ??  Ss   Tue08AM   0:06.66 \/usr\/sbin\/mDNSResponderHelper\nroot               184   0.0  0.0  2470768   2884   ??  Ss   Tue08AM   0:00.60 \/usr\/sbin\/systemstats --xpc\nroot               183   0.0  0.0  2496840   4840   ??  Ss   Tue08AM   0:01.53 \/usr\/libexec\/diskmanagementd\nroot               178   0.0  0.0  2471252   3792   ??  Ss   Tue08AM   0:04.07 \/System\/Library\/PrivateFrameworks\/CoreSymbolication.framework\/coresymbolicationd\nroot               167   0.0  0.0  2469440   3296   ??  Ss   Tue08AM   0:01.03 \/System\/Library\/CoreServices\/CrashReporterSupportHelper server-init\nroot               166   0.0  0.0  2495968   5916   ??  Ss   Tue08AM   0:03.27 \/System\/Library\/PrivateFrameworks\/WirelessDiagnostics.framework\/Support\/awdd\nroot               161   0.0  1.6  3795328 271848   ??  Ss   Tue08AM  13:25.55 \/System\/Library\/Frameworks\/CoreServices.framework\/Frameworks\/Metadata.framework\/Versions\/A\/Support\/mds_stores\nroot               160   0.0  0.4  2571344  70380   ??  Ss   Tue08AM   0:16.29 \/usr\/libexec\/sandboxd\n_coreaudiod        158   0.0  0.0  2495312   3888   ??  Ss   Tue08AM   0:01.54 \/System\/Library\/Frameworks\/CoreAudio.framework\/Versions\/A\/XPCServices\/com.apple.audio.DriverHelper.xpc\/Contents\/MacOS\/com.apple.audio.DriverHelper\nroot               157   0.0  0.1  2499628  11364   ??  Ss   Tue08AM   0:04.24 \/usr\/libexec\/lsd runAsRoot\n_coreaudiod        156   0.0  0.1  2499636  14228   ??  Ss   Tue08AM   7:17.85 \/usr\/sbin\/coreaudiod\n_mdnsresponder     149   0.0  0.0  2498688   7556   ??  Ss   Tue08AM   2:52.48 \/usr\/sbin\/mDNSResponder\n_ctkd              130   0.0  0.0  2471376   4520   ??  Ss   Tue08AM   0:00.60 \/System\/Library\/Frameworks\/CryptoTokenKit.framework\/ctkd -s\nroot               129   0.0  0.0  2500340   8108   ??  Ss   Tue08AM   0:15.97 \/usr\/libexec\/trustd\nroot               128   0.0  0.0  2470180   3360   ??  Ss   Tue08AM   0:00.83 \/System\/Library\/Frameworks\/PCSC.framework\/Versions\/A\/XPCServices\/com.apple.ctkpcscd.xpc\/Contents\/MacOS\/com.apple.ctkpcscd\nroot               116   0.0  0.0  2469980   3244   ??  Ss   Tue08AM   0:00.77 aslmanager\nroot               114   0.0  0.0  2531052   7884   ??  Ss   Tue08AM   0:06.79 \/System\/Library\/CoreServices\/coreservicesd\nroot               112   0.0  0.1  2498096   9548   ??  Ss   Tue08AM   0:02.82 \/System\/Library\/Frameworks\/Security.framework\/Versions\/A\/XPCServices\/authd.xpc\/Contents\/MacOS\/authd\nroot               111   0.0  0.0  2470024   3400   ??  Ss   Tue08AM   0:43.14 \/usr\/sbin\/cfprefsd daemon\n_distnote          108   0.0  0.0  2469460   3268   ??  Ss   Tue08AM   0:24.41 \/usr\/sbin\/distnoted daemon\nroot               107   0.0  0.1  2499868  10092   ??  Ss   Tue08AM   0:02.01 \/usr\/libexec\/amfid\nroot               106   0.0  0.0  2470528   2140   ??  Ss   Tue08AM   2:11.68 \/usr\/sbin\/notifyd\nroot               105   0.0  0.0  2496764   7056   ??  Ss   Tue08AM   0:06.49 \/usr\/libexec\/AirPlayXPCHelper\nroot               102   0.0  0.0  2461516   1256   ??  Ss   Tue08AM   0:00.01 \/usr\/sbin\/KernelEventAgent\nroot               101   0.0  0.0  2469488   3004   ??  Ss   Tue08AM   0:00.54 \/System\/Library\/CoreServices\/logind\nakrug              100   0.0  0.4  2607616  63948   ??  Ss   Tue08AM   0:50.03 \/System\/Library\/CoreServices\/loginwindow.app\/Contents\/MacOS\/loginwindow console\nroot                99   0.0  0.0  2497192   3992   ??  Ss   Tue08AM   0:01.34 \/System\/Library\/PrivateFrameworks\/GenerationalStorage.framework\/Versions\/A\/Support\/revisiond\nroot                96   0.0  0.0  2469936   2636   ??  Ss   Tue08AM   0:00.72 autofsd\nroot                95   0.0  0.0  2496976   7832   ??  Ss   Tue08AM   0:57.44 \/usr\/sbin\/blued\n_displaypolicyd     94   0.0  0.0  2471820   2864   ??  Ss   Tue08AM   1:55.87 \/usr\/libexec\/displaypolicyd -k 1\nroot                93   0.0  0.0  2499832   7332   ??  Ss   Tue08AM   0:27.61 \/usr\/libexec\/DuetHeuristic-BM\n_locationd          91   0.0  0.1  2505144   9988   ??  Ss   Tue08AM   0:32.94 \/usr\/libexec\/locationd\nroot                89   0.0  0.1  2498824   9580   ??  Ss   Tue08AM   0:10.89 \/usr\/sbin\/securityd -i\n_usbmuxd            88   0.0  0.0  2470076   2948   ??  Ss   Tue08AM   0:00.62 \/System\/Library\/PrivateFrameworks\/MobileDevice.framework\/Versions\/A\/Resources\/usbmuxd -launchd\nroot                87   0.0  0.1  2499740  10952   ??  Ss   Tue08AM   0:53.18 \/System\/Library\/CoreServices\/launchservicesd\nroot                86   0.0  0.0  2496156   3664   ??  Ss   Tue08AM   0:01.40 \/System\/Library\/PrivateFrameworks\/Noticeboard.framework\/Versions\/A\/Resources\/nbstated\nroot                85   0.0  0.0  2460800   1836   ??  Ss   Tue08AM   0:00.01 \/Library\/PrivilegedHelperTools\/com.docker.vmnetd\nroot                84   0.0  0.1  2498820  11184   ??  Ss   Tue08AM   0:47.83 \/System\/Library\/PrivateFrameworks\/ApplePushService.framework\/apsd\nroot                82   0.0  0.0  2496220   4304   ??  Ss   Tue08AM   0:14.88 \/usr\/sbin\/wirelessproxd\nroot                80   0.0  0.1  2513872  12792   ??  Ss   Tue08AM   1:38.27 \/usr\/libexec\/opendirectoryd\nroot                78   0.0  0.0  2469688   1892   ??  Ss   Tue08AM   2:20.97 \/System\/Library\/CoreServices\/ionodecache -k \/var\/db\/ionodecache.json\nroot                75   0.0  0.0  2471244   2032   ??  Ss   Tue08AM   0:00.03 \/usr\/libexec\/wdhelper\nroot                74   0.0  0.1  2504584  24676   ??  Ss   Tue08AM   1:20.65 \/usr\/libexec\/coreduetd\nroot                72   0.0  0.0  2494864   3488   ??  Ss   Tue08AM   0:02.16 \/usr\/libexec\/diskarbitrationd\nroot                70   0.0  0.0  2471116   1924   ??  Ss   Tue08AM   0:00.60 \/System\/Library\/CoreServices\/iconservicesagent\n_iconservices       69   0.0  0.0  2496740   4524   ??  Ss   Tue08AM   0:01.01 \/System\/Library\/CoreServices\/iconservicesd\nroot                64   0.0  0.4  2631708  59376   ??  Ss   Tue08AM   7:00.50 \/System\/Library\/Frameworks\/CoreServices.framework\/Frameworks\/Metadata.framework\/Support\/mds\nroot                62   0.0  0.0  2473540   7704   ??  SNs  Tue08AM   0:01.71 \/usr\/libexec\/warmd\nroot                61   0.0  0.1  2513132  15444   ??  Ss   Tue08AM  15:38.02 \/usr\/libexec\/airportd\nroot                57   0.0  0.1  2541388  24288   ??  Ss   Tue08AM   1:01.59 \/usr\/libexec\/logd\nroot                53   0.0  0.3  2509068  49652   ??  Ss   Tue08AM   0:07.24 \/usr\/libexec\/mobileassetd\nroot                52   0.0  0.0  2495592   4572   ??  Ss   Tue08AM   1:12.78 \/System\/Library\/CoreServices\/powerd.bundle\/powerd\nroot                51   0.0  0.1  2501040   9104   ??  Ss   Tue08AM   5:57.44 \/usr\/libexec\/configd\n_appleevents        50   0.0  0.0  2497132   5596   ??  Ss   Tue08AM   0:02.45 \/System\/Library\/CoreServices\/appleeventsd --server\nroot                47   0.0  0.0  2496484   7636   ??  Ss   Tue08AM   0:03.10 \/System\/Library\/PrivateFrameworks\/MediaRemote.framework\/Support\/mediaremoted\nroot                45   0.0  0.1  2481328  10684   ??  Ss   Tue08AM   0:52.22 \/System\/Library\/Frameworks\/CoreServices.framework\/Versions\/A\/Frameworks\/FSEvents.framework\/Versions\/A\/Support\/fseventsd\nroot                44   0.0  0.1  2501944  14948   ??  Ss   Tue08AM   0:04.21 \/usr\/libexec\/kextd\nroot                43   0.0  0.0  2469916   2508   ??  Ss   Tue08AM   0:06.91 \/System\/Library\/PrivateFrameworks\/Uninstall.framework\/Resources\/uninstalld\nroot                42   0.0  0.2  3808008  32664   ??  SNs  Tue08AM   1:11.05 \/Applications\/CrashPlan.app\/Contents\/MacOS\/CrashPlanService -Dapp=CrashPlanService -Xmn10m -Xms15m -Xmx1024m -DappBaseName=CrashPlan -Djava.awt.headless=true -Dfile.encoding=UTF-8 -Dsun.net.inetaddr.ttl=300 -Dnetworkaddress.cache.ttl=300 -Dsun.net.inetaddr.negative.ttl=0 -Dnetworkaddress.cache.negative.ttl=0 -DCP_USER_NAME= -DCP_USER_HOME= -cp lib\/com.backup42.desktop.jar:lang com.backup42.service.CPService CP_USER_NAME= CP_USER_HOME=\nroot                40   0.0  0.0  2471632   1280   ??  Ss   Tue08AM   0:21.35 \/usr\/sbin\/syslogd\nroot                39   0.0  0.1  2501904  17676   ??  Ss   Tue08AM   2:03.74 \/usr\/libexec\/UserEventAgent (System)\nroot                 1   0.0  0.1  2492548  15488   ??  Ss   Tue08AM   8:07.87 \/sbin\/launchd\nakrug            40996   0.0  0.0        0      0 s000  Z+    8:57AM   0:00.00 (dmesg)\nakrug            40995   0.0  0.0        0      0 s000  Z+    8:57AM   0:00.00 (df)\nroot             40997   0.0  0.0  2434200   1008 s000  R+    8:57AM   0:00.00 ps aux\nakrug            40994   0.0  0.0        0      0 s000  Z+    8:57AM   0:00.00 (uname)\nakrug            40943   0.0  0.1  3013164   9580   ??  S     8:54AM   0:00.10 \/System\/Library\/Frameworks\/QuickLook.framework\/Resources\/quicklookd.app\/Contents\/MacOS\/quicklookd\nakrug            40787   0.0  0.1  2652444  18936   ??  S     8:42AM   0:00.11 \/Users\/akrug\/Applications\/Chrome Apps.localized\/Default hgmloofddffdnphfgcellkdfbfbjeloo.app\/Contents\/MacOS\/app_mode_loader --launched-by-chrome-process-id=37198\nakrug            40786   0.0  1.1  4560340 177388   ??  S     8:42AM   0:12.97 \/Applications\/Google Chrome.app\/Contents\/Versions\/56.0.2924.87\/Google Chrome Helper.app\/Contents\/MacOS\/Google Chrome Helper --type=renderer --enable-features=AutofillProfileCleanup<AutofillProfileCleanup,BlockSmallPluginContent<PluginPowerSaverTiny,EnableSyncClientToServerCompression<EnableSyncClientToServerCompression,*ExpectCTReporting<ExpectCTReporting,*NegotiateTLS13<TLS13Negotiation,ParseHTMLOnMainThread<ParseHTMLOnMainThread,*PersistentHistograms<PersistentHistograms,*PointerEvent<PointerEvent,PreferHtmlOverPlugins<Html5ByDefault,*PrioritySupportedRequestsDelayable<NetDelayableH2AndQuicRequests,SecurityChip<SecurityChip,SecurityWarningIconUpdate<SecurityWarningIconUpdate,SubresourceFilter<SubresourceFilter,*TranslateRankerLogging<TranslateRankerLogging,ViewsSimplifiedFullscreenUI<ViewsSimplifiedFullscreenUI --disable-features=DocumentWriteEvaluator<DisallowFetchForDocWrittenScriptsInMainFrame,SSLPostQuantumExperiment<SSLPostQuantum --force-fieldtrials=*AppBannerTriggering\/site-engagement-eager\/*AutofillProfileCleanup\/Enabled\/CaptivePortalInterstitial\/Enabled\/*ChromeChannelStable\/Enabled\/*ChromeSuggestionsTuning\/Default\/*ClientSideDetectionModel\/Model0\/*DataReductionProxyUseQuic\/ControlForTcpLowat\/*DisallowFetchForDocWrittenScriptsInMainFrame\/Control_20161208_Launch\/EnableSyncClientToServerCompression\/Enabled\/ExpectCTReporting\/ExpectCTReportingDisabled\/*ExtensionDeveloperModeWarning\/Enabled\/*ExtensionInstallVerification\/Enforce\/*Html5ByDefault\/Enabled2\/*InstanceID\/Enabled\/MarkNonSecureAs\/show-non-secure-passwords-cc-ui\/*NetDelayableH2AndQuicRequests\/Default\/OfferUploadCreditCards\/Enabled\/*OmniboxBundledExperimentV1\/StandardR7\/*ParseHTMLOnMainThread\/Default\/PasswordBranding\/SmartLockBrandingSavePromptOnly\/*PasswordGeneration\/Disabled\/*PasswordManagerSettingsMigration\/Enable\/*PersistentHistograms\/Default\/PluginPowerSaverTiny\/Enabled2\/*QUIC\/EnabledNoId\/ReportCertificateErrors\/ShowAndPossiblySend\/SHA1IdentityUIWarning\/Enabled\/SHA1ToolbarUIJanuary2016\/Warning\/SHA1ToolbarUIJanuary2017\/Error\/SSLCommonNameMismatchHandling\/Enabled\/*SSLPostQuantum\/disabled\/*SafeBrowsingIncidentReportingService\/Default\/SafeBrowsingUnverifiedDownloads\/DisableByParameterMostSbTypes2\/SafeBrowsingV4LocalDatabaseManagerEnabled\/Default\/*SaveAsMenuText\/default\/*SecurityChip\/Enabled\/SecurityWarningIconUpdate\/Enabled2\/SignInPasswordPromo\/Enable3\/*SiteIsolationExtensions\/Enabled_100\/*StrictSecureCookies\/Enabled\/*SubresourceFilter\/EnabledForPhishingSites\/*TLS13Negotiation\/Default\/*TranslateRankerLogging\/TranslateRankerLoggingDefault\/TranslateServerStudy\/Default\/*UMA-Dynamic-Uniformity-Trial\/Group3\/*UMA-Population-Restrict\/normal\/*UMA-Uniformity-Trial-1-Percent\/group_11\/*UMA-Uniformity-Trial-10-Percent\/group_05\/*UMA-Uniformity-Trial-100-Percent\/group_01\/*UMA-Uniformity-Trial-20-Percent\/group_03\/*UMA-Uniformity-Trial-5-Percent\/group_11\/*UMA-Uniformity-Trial-50-Percent\/default\/*WebFontsInterventionV2\/Default\/ --primordial-pipe-token=FED5F0EB399E48F3C8E5F0847B93C960 --lang=en-US --metrics-client-id=14916563-c75e-480b-b431-86b7db92b357 --extension-process --enable-offline-auto-reload --enable-offline-auto-reload-visible-only --blink-settings=disallowFetchForDocWrittenScriptsInMainFrame=false,disallowFetchForDocWrittenScriptsInMainFrameOnSlowConnections=false --enable-pinch --num-raster-threads=2 --enable-gpu-rasterization --enable-zero-copy --enable-gpu-memory-buffer-compositor-resources --enable-main-frame-before-activation --content-image-texture-target=0,0,3553;0,1,3553;0,2,3553;0,3,3553;0,4,3553;0,5,3553;0,6,3553;0,7,3553;0,8,3553;0,9,3553;0,10,34037;0,11,34037;0,12,34037;0,13,3553;0,14,3553;0,15,3553;1,0,3553;1,1,3553;1,2,3553;1,3,3553;1,4,3553;1,5,3553;1,6,3553;1,7,3553;1,8,3553;1,9,3553;1,10,34037;1,11,34037;1,12,34037;1,13,3553;1,14,3553;1,15,3553;2,0,3553;2,1,3553;2,2,3553;2,3,3553;2,4,3553;2,5,34037;2,6,3553;2,7,3553;2,8,3553;2,9,3553;2,10,3553;2,11,3553;2,12,34037;2,13,3553;2,14,34037;2,15,34037;3,0,3553;3,1,3553;3,2,3553;3,3,3553;3,4,3553;3,5,34037;3,6,3553;3,7,3553;3,8,3553;3,9,3553;3,10,3553;3,11,3553;3,12,34037;3,13,3553;3,14,34037;3,15,34037 --service-request-channel-token=FED5F0EB399E48F3C8E5F0847B93C960 --renderer-client-id=1013\nakrug            40784   0.0  0.4  3293088  65336   ??  S     8:42AM   0:00.93 \/Applications\/Google Chrome.app\/Contents\/Versions\/56.0.2924.87\/Google Chrome Helper.app\/Contents\/MacOS\/Google Chrome Helper --type=renderer --enable-features=AutofillProfileCleanup<AutofillProfileCleanup,BlockSmallPluginContent<PluginPowerSaverTiny,EnableSyncClientToServerCompression<EnableSyncClientToServerCompression,*ExpectCTReporting<ExpectCTReporting,*NegotiateTLS13<TLS13Negotiation,ParseHTMLOnMainThread<ParseHTMLOnMainThread,*PersistentHistograms<PersistentHistograms,*PointerEvent<PointerEvent,PreferHtmlOverPlugins<Html5ByDefault,*PrioritySupportedRequestsDelayable<NetDelayableH2AndQuicRequests,SecurityChip<SecurityChip,SecurityWarningIconUpdate<SecurityWarningIconUpdate,SubresourceFilter<SubresourceFilter,*TranslateRankerLogging<TranslateRankerLogging,ViewsSimplifiedFullscreenUI<ViewsSimplifiedFullscreenUI --disable-features=DocumentWriteEvaluator<DisallowFetchForDocWrittenScriptsInMainFrame,SSLPostQuantumExperiment<SSLPostQuantum --force-fieldtrials=*AppBannerTriggering\/site-engagement-eager\/*AutofillProfileCleanup\/Enabled\/CaptivePortalInterstitial\/Enabled\/*ChromeChannelStable\/Enabled\/*ChromeSuggestionsTuning\/Default\/*ClientSideDetectionModel\/Model0\/*DataReductionProxyUseQuic\/ControlForTcpLowat\/*DisallowFetchForDocWrittenScriptsInMainFrame\/Control_20161208_Launch\/EnableSyncClientToServerCompression\/Enabled\/ExpectCTReporting\/ExpectCTReportingDisabled\/*ExtensionDeveloperModeWarning\/Enabled\/*ExtensionInstallVerification\/Enforce\/*Html5ByDefault\/Enabled2\/*InstanceID\/Enabled\/MarkNonSecureAs\/show-non-secure-passwords-cc-ui\/*NetDelayableH2AndQuicRequests\/Default\/OfferUploadCreditCards\/Enabled\/*OmniboxBundledExperimentV1\/StandardR7\/*ParseHTMLOnMainThread\/Default\/PasswordBranding\/SmartLockBrandingSavePromptOnly\/*PasswordGeneration\/Disabled\/*PasswordManagerSettingsMigration\/Enable\/*PersistentHistograms\/Default\/PluginPowerSaverTiny\/Enabled2\/*QUIC\/EnabledNoId\/ReportCertificateErrors\/ShowAndPossiblySend\/SHA1IdentityUIWarning\/Enabled\/SHA1ToolbarUIJanuary2016\/Warning\/SHA1ToolbarUIJanuary2017\/Error\/SSLCommonNameMismatchHandling\/Enabled\/*SSLPostQuantum\/disabled\/*SafeBrowsingIncidentReportingService\/Default\/SafeBrowsingUnverifiedDownloads\/DisableByParameterMostSbTypes2\/SafeBrowsingV4LocalDatabaseManagerEnabled\/Default\/*SaveAsMenuText\/default\/*SecurityChip\/Enabled\/SecurityWarningIconUpdate\/Enabled2\/SignInPasswordPromo\/Enable3\/*SiteIsolationExtensions\/Enabled_100\/*StrictSecureCookies\/Enabled\/*SubresourceFilter\/EnabledForPhishingSites\/*TLS13Negotiation\/Default\/*TranslateRankerLogging\/TranslateRankerLoggingDefault\/TranslateServerStudy\/Default\/*UMA-Dynamic-Uniformity-Trial\/Group3\/*UMA-Population-Restrict\/normal\/*UMA-Uniformity-Trial-1-Percent\/group_11\/*UMA-Uniformity-Trial-10-Percent\/group_05\/*UMA-Uniformity-Trial-100-Percent\/group_01\/*UMA-Uniformity-Trial-20-Percent\/group_03\/*UMA-Uniformity-Trial-5-Percent\/group_11\/*UMA-Uniformity-Trial-50-Percent\/default\/*WebFontsInterventionV2\/Default\/ --primordial-pipe-token=686455C5464077C25CAB9BF16BE8E905 --lang=en-US --metrics-client-id=14916563-c75e-480b-b431-86b7db92b357 --enable-offline-auto-reload --enable-offline-auto-reload-visible-only --blink-settings=disallowFetchForDocWrittenScriptsInMainFrame=false,disallowFetchForDocWrittenScriptsInMainFrameOnSlowConnections=false --enable-pinch --num-raster-threads=2 --enable-gpu-rasterization --enable-zero-copy --enable-gpu-memory-buffer-compositor-resources --enable-main-frame-before-activation --content-image-texture-target=0,0,3553;0,1,3553;0,2,3553;0,3,3553;0,4,3553;0,5,3553;0,6,3553;0,7,3553;0,8,3553;0,9,3553;0,10,34037;0,11,34037;0,12,34037;0,13,3553;0,14,3553;0,15,3553;1,0,3553;1,1,3553;1,2,3553;1,3,3553;1,4,3553;1,5,3553;1,6,3553;1,7,3553;1,8,3553;1,9,3553;1,10,34037;1,11,34037;1,12,34037;1,13,3553;1,14,3553;1,15,3553;2,0,3553;2,1,3553;2,2,3553;2,3,3553;2,4,3553;2,5,34037;2,6,3553;2,7,3553;2,8,3553;2,9,3553;2,10,3553;2,11,3553;2,12,34037;2,13,3553;2,14,34037;2,15,34037;3,0,3553;3,1,3553;3,2,3553;3,3,3553;3,4,3553;3,5,34037;3,6,3553;3,7,3553;3,8,3553;3,9,3553;3,10,3553;3,11,3553;3,12,34037;3,13,3553;3,14,34037;3,15,34037 --service-request-channel-token=686455C5464077C25CAB9BF16BE8E905 --renderer-client-id=1011\nakrug            40762   0.0  0.2  2500128  30236   ??  S     8:40AM   0:00.30 \/System\/Library\/Frameworks\/CoreServices.framework\/Frameworks\/Metadata.framework\/Versions\/A\/Support\/mdworker -s mdworker -c MDSImporterWorker -m com.apple.mdworker.shared\nakrug            40761   0.0  0.3  2513200  51004   ??  S     8:40AM   0:00.77 \/System\/Library\/Frameworks\/CoreServices.framework\/Frameworks\/Metadata.framework\/Versions\/A\/Support\/mdworker -s mdworker -c MDSImporterWorker -m com.apple.mdworker.shared\nakrug            40759   0.0  0.3  2522864  57876   ??  S     8:40AM   0:00.90 \/System\/Library\/Frameworks\/CoreServices.framework\/Frameworks\/Metadata.framework\/Versions\/A\/Support\/mdworker -s mdworker -c MDSImporterWorker -m com.apple.mdworker.shared\nakrug            40755   0.0  0.3  2517700  53616   ??  S     8:40AM   0:01.04 \/System\/Library\/Frameworks\/CoreServices.framework\/Frameworks\/Metadata.framework\/Versions\/A\/Support\/mdworker -s mdworker -c MDSImporterWorker -m com.apple.mdworker.shared\nakrug            40754   0.0  0.0  2462524   3276 s002  S+    8:40AM   0:00.14 ssh ec2-user@ec2-35-167-143-172.us-west-2.compute.amazonaws.com\nakrug            40700   0.0  0.0  2461044   3172 s002  S     8:40AM   0:00.06 -bash\nroot             40699   0.0  0.0  2469468   2740 s002  S     8:40AM   0:00.01 login -fp akrug\nakrug            40698   0.0  0.0  2480036   5536 s002  Ss    8:40AM   0:00.02 \/Applications\/iTerm.app\/Contents\/MacOS\/iTerm2 --server login -fp akrug\nakrug            40671   0.0  0.0  2462524   3328 s001  S+    8:35AM   0:00.19 ssh ec2-user@ec2-35-167-143-172.us-west-2.compute.amazonaws.com\nakrug            40617   0.0  0.0  2452852   3020 s001  S     8:35AM   0:00.06 -bash\nroot             40616   0.0  0.0  2469468   2696 s001  S     8:35AM   0:00.01 login -fp akrug\nakrug            40615   0.0  0.0  2480036   5532 s001  Ss    8:35AM   0:00.02 \/Applications\/iTerm.app\/Contents\/MacOS\/iTerm2 --server login -fp akrug\nakrug            40393   0.0  0.0  2497432   6212   ??  Ss    8:25AM   0:00.04 \/System\/Library\/PrivateFrameworks\/XprotectFramework.framework\/Versions\/A\/XPCServices\/XprotectService.xpc\/Contents\/MacOS\/XprotectService\n"
}
